Metadata-Version: 1.0
Name: smooth-stream
Version: 0.0.1
Summary: Webcam, PiCamera Streaming over the Network in Python made easy.
Home-page: https://github.com/CT83/SmoothStream
Author: rohan
Author-email: rohansawantct83@gmail.com
License: GPLv3
Platform: UNKNOWN
